{
  "total_posts_loaded": 38338,
  "total_relevant": 16638,
  "total_insights": 9827,
  "unique_sources": 59,
  "source_distribution": {
    "eBay Forums": 2358,
    "Reddit": 1249,
    "Industry Analysis": 787,
    "Seller Community": 492,
    "App Reviews": 475,
    "Whatnot": 380,
    "Twitter/X": 368,
    "PSA Forums": 280,
    "Fanatics Collect": 231,
    "Sports Card Forum": 207,
    "Heritage Blog": 199,
    "TCGPlayer": 179,
    "Alt.xyz Blog": 169,
    "PSA Consignment": 168,
    "Beckett": 167,
    "Trustpilot:eBay": 158,
    "Heritage Auctions": 148,
    "Bluesky": 122,
    "COMC": 120,
    "Blowout Forums": 119,
    "Bench Trading": 108,
    "ConsumerAffairs:eBay": 108,
    "Trustpilot:Heritage": 107,
    "Trustpilot:Whatnot": 105,
    "Card Ladder": 103,
    "Podcast": 98,
    "Goldin": 98,
    "Goldin Blog": 94,
    "Trustpilot:Goldin": 92,
    "Cllct": 77,
    "Trustpilot:TCGPlayer": 72,
    "SGC": 50,
    "Collectors Universe": 46,
    "YouTube (comment)": 42,
    "Vinted": 29,
    "News:Cardboard Connection": 20,
    "Cardboard Connection": 20,
    "Sports Card Club": 19,
    "Mantel News": 18,
    "YouTube": 13,
    "Fanatics Live": 12,
    "Freedom Cardboard": 12,
    "News:Beckett News": 11,
    "News:Blowout Buzz": 11,
    "News:Just Collect Blog": 11,
    "News:Cardlines": 10,
    "Reddit (Blowout mention)": 10,
    "News:Dave and Adams": 9,
    "YouTube (transcript)": 9,
    "Net54 Baseball": 8,
    "Courtyard": 6,
    "News:Mantel News": 5,
    "Lelands": 5,
    "Alt": 4,
    "SCP Auctions": 2,
    "Google News (Blowout)": 2,
    "eBay Inc. Blog": 2,
    "Gold Card Auctions": 2,
    "Sports Card Investor": 1
  },
  "generated_at": "2026-03-22T10:13:18.820494"
}